openseespytools/__init__.py
openseespytools/data.py
openseespytools/model.py
openseespytools/model_database.py
openseespytools/response.py
openseespytools/stylesheets.py
openseespytools-0.4.0.dist-info/METADATA
openseespytools-0.4.0.dist-info/WHEEL
openseespytools-0.4.0.dist-info/license.txt
openseespytools-0.4.0.dist-info/top_level.txt
openseespytools-0.4.0.dist-info/RECORD
