Metadata-Version: 2.1
Name: openseespytools
Version: 0.4.0
Summary: Postprocessing tools for OpenSeesPy
Home-page: https://github.com/cslotboom/openseesPyTools
Author: Christian Slotboom
Author-email: cslotboom@yahoo.com
License: UNKNOWN
Platform: UNKNOWN
Classifier: Programming Language :: Python :: 3
Classifier: License :: OSI Approved :: MIT License
Classifier: Operating System :: OS Independent
Requires-Python: >=3.6
